win_basic_tools/__init__.py
win_basic_tools/__main__.py
win_basic_tools/setup_cmd.py
win_basic_tools-0.4.2.dist-info/LICENSE
win_basic_tools-0.4.2.dist-info/METADATA
win_basic_tools-0.4.2.dist-info/WHEEL
win_basic_tools-0.4.2.dist-info/entry_points.txt
win_basic_tools-0.4.2.dist-info/top_level.txt
win_basic_tools-0.4.2.dist-info/RECORD
