Metadata-Version: 2.1
Name: win-basic-tools
Version: 0.4.2
Summary: Cli tool for listing the directory.
Author: Henrique do Val
Author-email: henrique.val@hotmail.com
License: MIT
Project-URL: Home-page, https://github.com/HenriquedoVal/win-basic-tools
Classifier: Programming Language :: Python :: 3 :: Only
Classifier: Programming Language :: Python :: Implementation :: CPython
Classifier: Programming Language :: Python :: Implementation :: PyPy
Classifier: License :: OSI Approved :: MIT License
Classifier: Development Status :: 4 - Beta
Classifier: Operating System :: Microsoft :: Windows
Classifier: Environment :: Console
Classifier: Intended Audience :: Developers
Classifier: Topic :: System :: Shells
Classifier: Topic :: Terminals
Requires-Python: >=3.6
License-File: LICENSE
Requires-Dist: colorama >=0.4.6
